jaraco/structures/__init__.py
jaraco/structures/binary.py
jaraco.structures-2.2.0.dist-info/LICENSE
jaraco.structures-2.2.0.dist-info/METADATA
jaraco.structures-2.2.0.dist-info/WHEEL
jaraco.structures-2.2.0.dist-info/top_level.txt
jaraco.structures-2.2.0.dist-info/RECORD
